liqpy/__init__.py
liqpy/__main__.py
liqpy/client.py
liqpy/pandas.py
liqpy/api/__init__.py
liqpy/api/decoder.py
liqpy/api/encoder.py
liqpy/api/exceptions.py
liqpy/api/validation.py
liqpy/dev/__init__.py
liqpy/dev/server.py
liqpy/dev/testing.py
liqpy/models/__init__.py
liqpy/models/report.py
liqpy/models/request.py
liqpy/types/__init__.py
liqpy/types/error.py
liqpy/types/request.py
liqpy/types/response.py
liqpy-0.20.0.dist-info/METADATA
liqpy-0.20.0.dist-info/WHEEL
liqpy-0.20.0.dist-info/licenses/LICENSE
liqpy-0.20.0.dist-info/RECORD
