Metadata-Version: 2.4
Name: liqpy
Version: 0.20.0
Summary: Unofficial Python libary for LiqPay API
Project-URL: Repository, https://github.com/rostyq/liqpy
Author-email: Rostyslav Bohomaz <rostyslav.db@gmail.com>
License: MIT License
License-File: LICENSE
Keywords: api,liqpay
Classifier: Programming Language :: Python :: 3
Requires-Python: >=3.11
Requires-Dist: httpx>=0.28.0
